fast_hist_package/__init__.py
fast_hist_package/model_fast_hist.py
fast_hist_package-0.1.0.dist-info/METADATA
fast_hist_package-0.1.0.dist-info/WHEEL
fast_hist_package-0.1.0.dist-info/top_level.txt
fast_hist_package-0.1.0.dist-info/RECORD
